PolibasePersonNotificationAnswerService/__init__.py
PolibasePersonNotificationAnswerService/__main__.py
PolibasePersonNotificationAnswerService/const.py
PolibasePersonNotificationAnswerService/service.py
pih_plb_ntf_answ-0.13.dist-info/METADATA
pih_plb_ntf_answ-0.13.dist-info/WHEEL
pih_plb_ntf_answ-0.13.dist-info/entry_points.txt
pih_plb_ntf_answ-0.13.dist-info/top_level.txt
pih_plb_ntf_answ-0.13.dist-info/RECORD
